webhook_receiver/__init__.py
webhook_receiver/flask_utils.py
webhook_receiver/github_webhooks.py
webhook_receiver/gitlab_webhooks.py
webhook_receiver/webhooks.py
webhook_receiver/event/__init__.py
ebhook_receiver-0.0.2.dist-info/METADATA
ebhook_receiver-0.0.2.dist-info/WHEEL
ebhook_receiver-0.0.2.dist-info/top_level.txt
ebhook_receiver-0.0.2.dist-info/RECORD
